README.md
setup.py
TextEncrypt/AES_encrypt.py
TextEncrypt/__init__.py
TextEncrypt.egg-info/PKG-INFO
TextEncrypt.egg-info/SOURCES.txt
TextEncrypt.egg-info/dependency_links.txt
TextEncrypt.egg-info/entry_points.txt
TextEncrypt.egg-info/requires.txt
TextEncrypt.egg-info/top_level.txt