Metadata-Version: 2.1
Name: TextEncrypt
Version: 0.3.4
Summary: TextEncrypt: encrypt and decrypt the text of a file
Home-page: https://github.com/aiyacharley/TextEncrypt
Author: Chengrui Wang
Author-email: aiyacharley@outlook.com
Maintainer: Chengrui Wang
Maintainer-email: aiyacharley@outlook.com
License: BSD (3-clause)
Download-URL: https://github.com/aiyacharley/TextEncrypt
Platform: UNKNOWN
Classifier: Intended Audience :: Science/Research
Classifier: Programming Language :: Python :: 3
Classifier: License :: OSI Approved :: BSD License
Classifier: Topic :: Security
Classifier: Topic :: Text Processing
Classifier: Operating System :: Microsoft :: Windows
